odoo10_addon_portal_partner_select_all-10.0.1.0.1.99.dev5-py3.8-nspkg.pth
odoo/addons/portal_partner_select_all/README.rst
odoo/addons/portal_partner_select_all/__init__.py
odoo/addons/portal_partner_select_all/__manifest__.py
odoo/addons/portal_partner_select_all/i18n/portal_partner_select_all.pot
odoo/addons/portal_partner_select_all/readme/CONTRIBUTORS.rst
odoo/addons/portal_partner_select_all/readme/DESCRIPTION.rst
odoo/addons/portal_partner_select_all/readme/USAGE.rst
odoo/addons/portal_partner_select_all/static/description/icon.png
odoo/addons/portal_partner_select_all/static/description/index.html
odoo/addons/portal_partner_select_all/wizard/__init__.py
odoo/addons/portal_partner_select_all/wizard/portal_wizard.py
odoo/addons/portal_partner_select_all/wizard/portal_wizard.xml
odoo10_addon_portal_partner_select_all-10.0.1.0.1.99.dev5.dist-info/METADATA
odoo10_addon_portal_partner_select_all-10.0.1.0.1.99.dev5.dist-info/WHEEL
odoo10_addon_portal_partner_select_all-10.0.1.0.1.99.dev5.dist-info/namespace_packages.txt
odoo10_addon_portal_partner_select_all-10.0.1.0.1.99.dev5.dist-info/top_level.txt
odoo10_addon_portal_partner_select_all-10.0.1.0.1.99.dev5.dist-info/RECORD
